doc/conf.py
snippets/test_sinogram.py
tomoscan/_CoordinateSystem.py
tomoscan/__init__.py
tomoscan/factory.py
tomoscan/framereducerbase.py
tomoscan/identifier.py
tomoscan/io.py
tomoscan/progress.py
tomoscan/scanbase.py
tomoscan/scanfactory.py
tomoscan/serie.py
tomoscan/series.py
tomoscan/source.py
tomoscan/test.py
tomoscan/tomoobject.py
tomoscan/validator.py
tomoscan/version.py
tomoscan/volumebase.py
tomoscan/esrf/__init__.py
tomoscan/esrf/edfscan.py
tomoscan/esrf/hdf5scan.py
tomoscan/esrf/mock.py
tomoscan/esrf/utils.py
tomoscan/esrf/identifier/__init__.py
tomoscan/esrf/identifier/edfidentifier.py
tomoscan/esrf/identifier/folderidentifier.py
tomoscan/esrf/identifier/hdf5Identifier.py
tomoscan/esrf/identifier/jp2kidentifier.py
tomoscan/esrf/identifier/rawidentifier.py
tomoscan/esrf/identifier/tiffidentifier.py
tomoscan/esrf/identifier/url_utils.py
tomoscan/esrf/identifier/tests/test_edfidentifier.py
tomoscan/esrf/identifier/tests/test_hdf5identifier.py
tomoscan/esrf/identifier/tests/test_rawidentifier.py
tomoscan/esrf/scan/__init__.py
tomoscan/esrf/scan/edfscan.py
tomoscan/esrf/scan/fscan.py
tomoscan/esrf/scan/fscan_scantypes.py
tomoscan/esrf/scan/h5utils.py
tomoscan/esrf/scan/hdf5scan.py
tomoscan/esrf/scan/mock.py
tomoscan/esrf/scan/nxtomoscan.py
tomoscan/esrf/scan/utils.py
tomoscan/esrf/scan/framereducer/__init__.py
tomoscan/esrf/scan/framereducer/edfframereducer.py
tomoscan/esrf/scan/framereducer/hdf5framereducer.py
tomoscan/esrf/scan/framereducer/tests/test_edfframereducer.py
tomoscan/esrf/scan/framereducer/tests/test_hdf5framereducer.py
tomoscan/esrf/scan/tests/test_edfscan.py
tomoscan/esrf/scan/tests/test_fscan.py
tomoscan/esrf/scan/tests/test_mock.py
tomoscan/esrf/scan/tests/test_nxtomoscan.py
tomoscan/esrf/scan/tests/test_nxtomoscan_mcstas.py
tomoscan/esrf/scan/tests/test_utils.py
tomoscan/esrf/volume/__init__.py
tomoscan/esrf/volume/edfvolume.py
tomoscan/esrf/volume/hdf5volume.py
tomoscan/esrf/volume/jp2kvolume.py
tomoscan/esrf/volume/mock.py
tomoscan-2.3.2.dist-info/licenses/LICENSE
tomoscan-2.3.2.dist-info/METADATA
tomoscan-2.3.2.dist-info/WHEEL
tomoscan-2.3.2.dist-info/entry_points.txt
tomoscan-2.3.2.dist-info/top_level.txt
tomoscan-2.3.2.dist-info/RECORD
