Metadata-Version: 2.4
Name: tomoscan
Version: 2.3.2
Summary: Utility to access tomography data at ESRF
Author-email: Henri Payno <henri.payno@esrf.fr>, Pierre Paleo <pierre.paleo@esrf.fr>, Pierre-Olivier Autran <pierre-olivier.autran@esrf.fr>, Jérôme Lesaint <jerome.lesaint@esrf.fr>, Alessandro Mirone <mirone@esrf.fr>
License: MIT
Keywords: NXtomo,nexus,tomography,esrf,bliss-tomo
Classifier: Intended Audience :: Education
Classifier: Intended Audience :: Science/Research
Classifier: Programming Language :: Python :: 3
Classifier: Programming Language :: Python :: 3.10
Classifier: Programming Language :: Python :: 3.11
Classifier: Programming Language :: Python :: 3.12
Classifier: Programming Language :: Python :: 3.13
Classifier: Environment :: Console
Classifier: Environment :: X11 Applications :: Qt
Classifier: Operating System :: POSIX
Classifier: Natural Language :: English
Classifier: Topic :: Scientific/Engineering :: Physics
Classifier: Topic :: Software Development :: Libraries :: Python Modules
Requires-Python: >=3.10
License-File: LICENSE
Requires-Dist: setuptools
Requires-Dist: defusedxml
Requires-Dist: h5py>=3.0
Requires-Dist: silx>=2.0
Requires-Dist: lxml
Requires-Dist: dicttoxml
Requires-Dist: packaging
Requires-Dist: psutil
Requires-Dist: nxtomo>=3.0.0dev0
Requires-Dist: numpy
Requires-Dist: packaging>=22.0
Requires-Dist: pint
Provides-Extra: compression-plugins
Requires-Dist: hdf5plugin; extra == "compression-plugins"
Requires-Dist: blosc2-grok; extra == "compression-plugins"
Provides-Extra: full-no-compression-plugins
Requires-Dist: glymur; extra == "full-no-compression-plugins"
Requires-Dist: tqdm; extra == "full-no-compression-plugins"
Requires-Dist: tifffile[zarr]>=2023.7.4; extra == "full-no-compression-plugins"
Requires-Dist: zarr; extra == "full-no-compression-plugins"
Requires-Dist: fsspec; extra == "full-no-compression-plugins"
Provides-Extra: full
Requires-Dist: tomoscan[full_no_compression_plugins]; extra == "full"
Requires-Dist: tomoscan[compression_plugins]; extra == "full"
Provides-Extra: test
Requires-Dist: pytest; extra == "test"
Requires-Dist: python-gitlab; extra == "test"
Requires-Dist: glymur; extra == "test"
Requires-Dist: tqdm; extra == "test"
Requires-Dist: tifffile[zarr]>=2023.7.4; extra == "test"
Requires-Dist: zarr; extra == "test"
Requires-Dist: fsspec; extra == "test"
Provides-Extra: doc
Requires-Dist: Sphinx<5.2.0,>=4.0.0; extra == "doc"
Requires-Dist: nbsphinx; extra == "doc"
Requires-Dist: pandoc; extra == "doc"
Requires-Dist: ipykernel; extra == "doc"
Requires-Dist: jupyter_client; extra == "doc"
Requires-Dist: nbconvert; extra == "doc"
Requires-Dist: h5glance; extra == "doc"
Requires-Dist: pydata_sphinx_theme; extra == "doc"
Requires-Dist: sphinx-design; extra == "doc"
Requires-Dist: sphinx-autodoc-typehints; extra == "doc"
Requires-Dist: glymur; extra == "doc"
Requires-Dist: tqdm; extra == "doc"
Requires-Dist: tifffile[zarr]>=2023.7.4; extra == "doc"
Requires-Dist: zarr; extra == "doc"
Requires-Dist: fsspec; extra == "doc"
Requires-Dist: myst-parser; extra == "doc"
Dynamic: license-file
